pyasx/__init__.py
pyasx/config.py
pyasx/config.yml
pyasx/data/__init__.py
pyasx/data/companies.py
pyasx/data/securities.py
pyasx-3.0.0.dist-info/WHEEL
pyasx-3.0.0.dist-info/METADATA
pyasx-3.0.0.dist-info/RECORD
