Metadata-Version: 2.1
Name: pyasx
Version: 3.0.0
Summary: Python library to pull data from ASX.com.au
License: MIT
Author: JohnVonNeumann
Author-email: 18162779+JohnVonNeumann@users.noreply.github.com
Requires-Python: >=3.10,<4.0
Classifier: License :: OSI Approved :: MIT License
Classifier: Programming Language :: Python :: 3
Classifier: Programming Language :: Python :: 3.10
Requires-Dist: PyYAML (>=6.0,<7.0)
Requires-Dist: python-dateutil (>=2.8.2,<3.0.0)
Requires-Dist: requests (>=2.28.1,<3.0.0)
